simple_workflow-0.1.47.dist-info/zip-safe
simple_workflow-0.1.47.dist-info/metadata.json
simple_workflow-0.1.47.dist-info/RECORD
simple_workflow-0.1.47.dist-info/top_level.txt
simple_workflow-0.1.47.dist-info/WHEEL
simple_workflow-0.1.47.dist-info/METADATA
simple_workflow-0.1.47.dist-info/DESCRIPTION.rst
swf/exceptions.py
swf/utils.py
swf/__init__.py
swf/format.py
swf/constants.py
swf/settings.py
swf/core.py
swf/models/history.py
swf/models/activity.py
swf/models/workflow.py
swf/models/__init__.py
swf/models/domain.py
swf/models/base.py
swf/models/decision/marker.py
swf/models/decision/workflow.py
swf/models/decision/timer.py
swf/models/decision/__init__.py
swf/models/decision/task.py
swf/models/decision/base.py
swf/models/event/compiler.py
swf/models/event/marker.py
swf/models/event/workflow.py
swf/models/event/factory.py
swf/models/event/timer.py
swf/models/event/__init__.py
swf/models/event/task.py
swf/models/event/base.py
swf/models/history/builder.py
swf/models/history/__init__.py
swf/models/history/base.py
swf/querysets/history.py
swf/querysets/activity.py
swf/querysets/workflow.py
swf/querysets/__init__.py
swf/querysets/domain.py
swf/querysets/base.py
swf/actors/heartbeat.py
swf/actors/helpers.py
swf/actors/__init__.py
swf/actors/worker.py
swf/actors/decider.py
swf/actors/core.py
