Metadata-Version: 2.0
Name: simple-workflow
Version: 0.1.47
Summary: Amazon simple workflow service wrapper for python
Home-page: http://github.com/botify-labs/python-simple-workflow
Author: Oleiade
Author-email: tcrevon@gmail.com
License: MIT
Keywords: amazon simple wokflow swf python
Platform: UNKNOWN
Requires-Dist: boto
Requires-Dist: mock (==1.0.1)
Requires-Dist: xworkflows (==1.0.0)
